parapply/__init__.py
tests/__init__.py
tests/test_df.py
tests/test_split.py
tests/test_srs.py
parapply-0.0.2.dist-info/LICENSE.txt
parapply-0.0.2.dist-info/METADATA
parapply-0.0.2.dist-info/WHEEL
parapply-0.0.2.dist-info/top_level.txt
parapply-0.0.2.dist-info/RECORD
