Metadata-Version: 2.1
Name: parapply
Version: 0.0.2
Summary: A simple drop-in replacement for parallelized pandas `apply`
Home-page: https://github.com/tnwei/parapply
Author: Tan Nian Wei
Author-email: tannianwei@aggienetwork.com
License: UNKNOWN
Platform: UNKNOWN
Classifier: Programming Language :: Python :: 3
Classifier: License :: OSI Approved :: MIT License
Classifier: Operating System :: OS Independent
Requires-Python: >=3.5
Requires-Dist: numpy
Requires-Dist: pandas
Requires-Dist: joblib
